codesingnal_1_to_10/1_to_5.py
codesingnal_1_to_10/__init__.py
codesignal_1_to_10-0.0.1.dist-info/LICENSE
codesignal_1_to_10-0.0.1.dist-info/METADATA
codesignal_1_to_10-0.0.1.dist-info/WHEEL
codesignal_1_to_10-0.0.1.dist-info/top_level.txt
codesignal_1_to_10-0.0.1.dist-info/RECORD
